<?xml version="1.0" encoding="UTF-8"?>
<objects serializationModel="Studio.02.02.00">
	<object class="AudioFile" id="{3171865d-5c4b-471c-9e64-4a62361ee92e}">
		<property name="assetPath">
			<value>Footsteps_DirtyGround_Walk_06.wav</value>
		</property>
		<property name="frequencyInKHz">
			<value>48</value>
		</property>
		<property name="channelCount">
			<value>1</value>
		</property>
		<property name="length">
			<value>0.40439583333333334</value>
		</property>
		<relationship name="masterAssetFolder">
			<destination>{f3c491a6-a2e5-4378-bd1f-34d879974750}</destination>
		</relationship>
	</object>
</objects>
